prefect_airbyte/__init__.py
prefect_airbyte/_version.py
prefect_airbyte/client.py
prefect_airbyte/configuration.py
prefect_airbyte/connections.py
prefect_airbyte/exceptions.py
prefect_airbyte/flows.py
prefect_airbyte/server.py
prefect_airbyte-0.3.2.dist-info/LICENSE
prefect_airbyte-0.3.2.dist-info/METADATA
prefect_airbyte-0.3.2.dist-info/WHEEL
prefect_airbyte-0.3.2.dist-info/entry_points.txt
prefect_airbyte-0.3.2.dist-info/top_level.txt
prefect_airbyte-0.3.2.dist-info/RECORD
