Metadata-Version: 2.1
Name: prefect-airbyte
Version: 0.3.2
Summary: prefect-airbyte contains tasks for interacting with Airbyte instances
Home-page: https://github.com/PrefectHQ/prefect-airbyte
Author: Prefect Technologies, Inc.
Author-email: help@prefect.io
License: Apache License 2.0
Keywords: prefect
Classifier: Natural Language :: English
Classifier: Intended Audience :: Developers
Classifier: Intended Audience :: System Administrators
Classifier: License :: OSI Approved :: Apache Software License
Classifier: Programming Language :: Python :: 3 :: Only
Classifier: Programming Language :: Python :: 3.7
Classifier: Programming Language :: Python :: 3.8
Classifier: Programming Language :: Python :: 3.9
Classifier: Programming Language :: Python :: 3.10
Classifier: Topic :: Software Development :: Libraries
Requires-Python: >=3.7
License-File: LICENSE
Requires-Dist: prefect>=2.13.5
Provides-Extra: dev
Requires-Dist: pytest; extra == "dev"
Requires-Dist: black; extra == "dev"
Requires-Dist: flake8; extra == "dev"
Requires-Dist: mypy; extra == "dev"
Requires-Dist: mkdocs; extra == "dev"
Requires-Dist: mkdocs-material; extra == "dev"
Requires-Dist: mkdocstrings[python]; extra == "dev"
Requires-Dist: isort; extra == "dev"
Requires-Dist: pre-commit; extra == "dev"
Requires-Dist: pytest-asyncio; extra == "dev"
Requires-Dist: mock; python_version < "3.8" and extra == "dev"
Requires-Dist: mkdocs-gen-files; extra == "dev"
Requires-Dist: interrogate; extra == "dev"
Requires-Dist: coverage; extra == "dev"
Requires-Dist: respx; extra == "dev"
Requires-Dist: pillow; extra == "dev"
